scabbard/__init__.py
scabbard/access_token.py
scabbard/scabbard.py
scabbard/swagger.yaml
scabbard-0.2.1.dist-info/LICENSE
scabbard-0.2.1.dist-info/METADATA
scabbard-0.2.1.dist-info/WHEEL
scabbard-0.2.1.dist-info/top_level.txt
scabbard-0.2.1.dist-info/RECORD
