Metadata-Version: 2.1
Name: scabbard
Version: 0.2.1
Summary: Pythonic client for Sabre Dev Studio REST APIs
Home-page: https://github.com/bundgus/scabbard
Author: Mark Bundgus
Author-email: bundgus@gmail.com
License: BSD 3-Clause License
Platform: UNKNOWN
Classifier: Development Status :: 3 - Alpha
Classifier: Intended Audience :: Developers
Classifier: Topic :: Software Development :: Libraries :: Python Modules
Classifier: License :: OSI Approved :: BSD License
Classifier: Operating System :: OS Independent
Classifier: Programming Language :: Python :: 2.7
Classifier: Programming Language :: Python :: 3.4
Classifier: Programming Language :: Python :: 3.5
Classifier: Programming Language :: Python :: 3.6
Requires-Dist: bravado (>=9.2.2)
Requires-Dist: pytz
Requires-Dist: iso8601
Requires-Dist: requests (>=2.18)
